{
  "method": "ml-fallback",
  "decision": "BENIGN",
  "prediction": "Benign",
  "rule_hits": [],
  "cluster": {
    "cluster": 0,
    "label": "Benign Traffic",
    "description": "Normal, benign network traffic with no signs of malicious behaviour."
  },
  "suggestion": "No action required. Traffic appears benign.",
  "rule_time_ms": 0.57,
  "ml_time_ms": 885.42,
  "total_time_ms": 3035.36,
  "confidence": 87.63,
  "feature_importance": [],
  "class_probabilities": {
    "Benign": 87.63,
    "DoS/DDoS Attacks": 9.94,
    "Malware/Backdoor": 0.1,
    "Recon/Scanning": 2.33
  },
  "ground_truth": "Normal",
  "row": {
    "timestamp": 1775385345.1115189,
    "src_ip": "100.214.170.123",
    "dst_ip": "7.70.219.220",
    "src_port": 21,
    "dst_port": 50100,
    "proto": "tcp",
    "service": "dns",
    "state": "INT",
    "id": 8944,
    "dur": 4.743750942246829,
    "spkts": 1,
    "dpkts": 49,
    "sbytes": 306030,
    "dbytes": 190652,
    "rate": 47877.21340544073,
    "sttl": 9,
    "dttl": 0,
    "sload": 137968817.40017867,
    "dload": 3950596.348553689,
    "sloss": 23,
    "dloss": 50,
    "sinpkt": 0.0,
    "dinpkt": 0.0,
    "sjit": 42428.77314971596,
    "djit": 1533.9539016852627,
    "swin": 0,
    "stcpb": 240025707,
    "dtcpb": 0,
    "dwin": 399,
    "tcprtt": 0.0684686355509524,
    "synack": 0.0,
    "ackdat": 0.020187850475076097,
    "smean": 24,
    "dmean": 0,
    "trans_depth": 1,
    "response_body_len": 27463,
    "ct_srv_src": 5,
    "ct_state_ttl": 1,
    "ct_dst_ltm": 25,
    "ct_src_dport_ltm": 1,
    "ct_dst_sport_ltm": 4,
    "ct_dst_src_ltm": 8,
    "is_ftp_login": 0,
    "ct_ftp_cmd": 0,
    "ct_flw_http_mthd": 1,
    "ct_src_ltm": 10,
    "ct_srv_dst": 8,
    "is_sm_ips_ports": 0,
    "label": 0,
    "attack_cat": "Normal"
  }
}