{
  "method": "rule-based",
  "decision": "ATTACK",
  "prediction": "GENERIC",
  "rule_hits": [
    {
      "rule": "category_generic",
      "category": "generic",
      "severity": "MEDIUM",
      "remedy": "Investigate suspicious activity."
    }
  ],
  "cluster": {
    "cluster": 3,
    "label": "Cluster 3 \u2014 Generic Anomaly",
    "description": "Generic / unclassified anomaly \u2014 requires manual triage."
  },
  "suggestion": "Log and escalate to Tier-2 analyst. Correlate with other events in the same time window.",
  "rule_time_ms": 0.62,
  "ml_time_ms": 0,
  "total_time_ms": 0.67,
  "confidence": 100.0,
  "feature_importance": [],
  "class_probabilities": {},
  "ground_truth": "Generic",
  "row": {
    "timestamp": 1775385423.474769,
    "src_ip": "192.168.114.123",
    "dst_ip": "179.43.231.209",
    "src_port": 27017,
    "dst_port": 64583,
    "proto": "ospf",
    "service": "smtp",
    "state": "ECO",
    "id": 75143,
    "dur": 0.0,
    "spkts": 32,
    "dpkts": 0,
    "sbytes": 65269,
    "dbytes": 451786,
    "rate": 38723.11928184292,
    "sttl": 243,
    "dttl": 31,
    "sload": 127406239.76405397,
    "dload": 876666.7038759596,
    "sloss": 35,
    "dloss": 73,
    "sinpkt": 1076.496254015916,
    "dinpkt": 1915.3040827105192,
    "sjit": 68604.34210170755,
    "djit": 0.0,
    "swin": 251,
    "stcpb": 1585842580,
    "dtcpb": 0,
    "dwin": 124,
    "tcprtt": 0.0,
    "synack": 0.0003384998062810306,
    "ackdat": 0.11848492551784691,
    "smean": 186,
    "dmean": 418,
    "trans_depth": 0,
    "response_body_len": 0,
    "ct_srv_src": 17,
    "ct_state_ttl": 0,
    "ct_dst_ltm": 1,
    "ct_src_dport_ltm": 22,
    "ct_dst_sport_ltm": 9,
    "ct_dst_src_ltm": 1,
    "is_ftp_login": 0,
    "ct_ftp_cmd": 0,
    "ct_flw_http_mthd": 0,
    "ct_src_ltm": 1,
    "ct_srv_dst": 1,
    "is_sm_ips_ports": 0,
    "label": 1,
    "attack_cat": "Generic"
  }
}